FastWebHDFS/__init__.py
FastWebHDFS/base.py
FastWebHDFS/exceptions.py
FastWebHDFS/main.py
FastWebHDFS/mode/__init__.py
FastWebHDFS/mode/asynchronous/base.py
FastWebHDFS/mode/asynchronous/main.py
FastWebHDFS/mode/synchronous/base.py
FastWebHDFS/mode/synchronous/main.py
FastWebHDFS/utils.py
fastwebhdfs-0.1.0b20260131.dist-info/METADATA
fastwebhdfs-0.1.0b20260131.dist-info/WHEEL
fastwebhdfs-0.1.0b20260131.dist-info/RECORD
