Metadata-Version: 2.4
Name: FastWebHDFS
Version: 0.1.0b20260131
Summary: FastWebHDFS is an async-first Python client for WebHDFS, built for secure Hadoop clusters and modern, real-time workloads. It enables high-concurrency, low-latency access to HDFS opening up possibilities to build MCP and AI-driven applications, with support for secure authentication and a roadmap toward a powerful CLI and tooling.
Author: Ren Lionel H. Marcaida
Author-email: sick.datascientist@gmail.com
Maintainer: Ren Lionel H. Marcaida
Maintainer-email: sick.datascientist@gmail.com
Requires-Python: >=3.12
Classifier: Programming Language :: Python :: 3
Classifier: Programming Language :: Python :: 3.12
Classifier: Programming Language :: Python :: 3.13
Classifier: Programming Language :: Python :: 3.14
Requires-Dist: aiofiles (>=25.1.0,<25.2.0)
Requires-Dist: httpx (>=0.28.1,<0.29.0)
Requires-Dist: typer (>=0.21.1,<0.22.0)
